CHANGELOG.rst
LICENSE.txt
MANIFEST.in
README.rst
TODO.txt
setup.cfg
setup.py
shrink/__init__.py
shrink/command.py
shrink/compatibility.py
shrink/parser.py
shrink/utils.py
shrink.egg-info/PKG-INFO
shrink.egg-info/SOURCES.txt
shrink.egg-info/dependency_links.txt
shrink.egg-info/entry_points.txt
shrink.egg-info/not-zip-safe
shrink.egg-info/top_level.txt
shrink/data/example_shrink.cfg