Metadata-Version: 1.0
Name: shrink
Version: 1.1
Summary: Tool for minification of css and javascript files
Home-page: https://bitbucket.org/jeronimoalbi/shrink
Author: Jerónimo José Albi
Author-email: albi@wienfluss.net
License: BSD License
Keywords: minify javascript css yuicompressor
Platform: OS Independent
Classifier: Environment :: Console
Classifier: Intended Audience :: Developers
Classifier: License :: OSI Approved :: BSD License
Classifier: Operating System :: OS Independent
Classifier: Programming Language :: Python
Classifier: Programming Language :: Python :: 2.5
Classifier: Programming Language :: Python :: 2.6
Classifier: Programming Language :: Python :: 2.7
Classifier: Programming Language :: Python :: 3
Classifier: Programming Language :: Python :: 3.2
Classifier: Topic :: Utilities
